ca_taxes/__init__.py
ca_taxes/admin.py
ca_taxes/models.py
ca_taxes/tests.py
ca_taxes/management/__init__.py
ca_taxes/management/commands/__init__.py
ca_taxes/management/commands/cataxes.py
ca_taxes/migrations/0001_initial.py
ca_taxes/migrations/0002_auto_20150825_0119.py
ca_taxes/migrations/__init__.py
ca_taxes-1.0.dist-info/LICENSE
ca_taxes-1.0.dist-info/METADATA
ca_taxes-1.0.dist-info/WHEEL
ca_taxes-1.0.dist-info/top_level.txt
ca_taxes-1.0.dist-info/RECORD
