Metadata-Version: 2.1
Name: ca-taxes
Version: 1.0
Summary: Django App for handling California Taxes
Home-page: https://github.com/stasdavydov/ca-taxes
Author: Stas Davydov
Author-email: davidovsv@yandex.ru
License: Unlicense License
Platform: UNKNOWN
Classifier: Development Status :: 4 - Beta
Classifier: License :: OSI Approved :: The Unlicense (Unlicense)
Classifier: Programming Language :: Python :: 3
Classifier: Programming Language :: Python :: 3.8
Requires-Dist: requests
Requires-Dist: Django
